<manifest alg="2" build="2017.0.0.363" opt="true" iceEnabled="true" iceMarkupVersion="2" iceEnabledOptions="link,responsive,cachebuster" exportTarget="other" domain="F1.html" resolutions="1x" timestamp="1495594533523">
  <folder name="phone">
    <folder name="css">
      <file name="index.css" crc="4054877366" ref="phone>index"/>
    </folder>
    <file name="index.html" crc="3963783596" seo="true" mt="1495525637062" redirect="true"/>
  </folder>
  <folder name="css">
    <file name="site_global.css" crc="443350757"/>
    <file name="index.css" crc="58371178" ref="index"/>
  </folder>
  <folder name="scripts">
    <file name="jquery-1.8.3.min.js" crc="209076791" ref="index:phone>index"/>
    <file name="museutils.js" crc="163421577" ref="index:phone>index"/>
    <file name="whatinput.js" crc="86476730" ref="index:phone>index"/>
    <file name="museconfig.js" crc="36584860" ref="index:phone>index"/>
    <file name="jquery.watch.js" crc="104486786" ref="index:phone>index"/>
    <file name="require.js" crc="244322403" ref="index:phone>index"/>
  </folder>
  <folder name="images">
    <file name="final-01.png" crc="142918370" seo="true" ref="phone>index"/>
  </folder>
  <file name="index.html" crc="454710433" seo="true" mt="1495525457511" redirect="false"/>
</manifest>